dagster_ext/__init__.py
dagster_ext/extension.py
dagster_ext/main.py
dagster_ext/pass_through.py
files_dagster_ext/dagster/cookiecutter.json
files_dagster_ext/dagster/{{ cookiecutter.project_name }}/repository.py
files_dagster_ext/github/cookiecutter.json
meltano/edk/__init__.py
meltano/edk/extension.py
meltano/edk/logging.py
meltano/edk/models.py
meltano/edk/process.py
dagster_ext-0.1.3.dist-info/METADATA
dagster_ext-0.1.3.dist-info/WHEEL
dagster_ext-0.1.3.dist-info/entry_points.txt
dagster_ext-0.1.3.dist-info/RECORD
